CHANGELOG.rst
pytest_prefer_nested_dup_tests/__impl.py
pytest_prefer_nested_dup_tests/__init__.py
pytest_prefer_nested_dup_tests/py.typed
pytest_prefer_nested_dup_tests-0.1.0.dist-info/entry_points.txt
pytest_prefer_nested_dup_tests-0.1.0.dist-info/LICENSE
pytest_prefer_nested_dup_tests-0.1.0.dist-info/WHEEL
pytest_prefer_nested_dup_tests-0.1.0.dist-info/METADATA
pytest_prefer_nested_dup_tests-0.1.0.dist-info/RECORD
