Metadata-Version: 2.1
Name: pytest-prefer-nested-dup-tests
Version: 0.1.0
Summary: A Pytest plugin to drop duplicated tests during collection, but will prefer keeping nested packages.
Home-page: https://github.com/MarximusMaximus/pytest-prefer-nested-dup-tests
License: MIT
Author: Marximus Maximus
Author-email: marximus@marximus.com
Maintainer: Marximus Maximus
Maintainer-email: marximus@marximus.com
Requires-Python: >=3.8,<4
Classifier: Development Status :: 4 - Beta
Classifier: Framework :: Pytest
Classifier: Intended Audience :: Developers
Classifier: License :: OSI Approved :: MIT License
Classifier: Operating System :: OS Independent
Classifier: Programming Language :: Python
Classifier: Programming Language :: Python :: 3
Classifier: Programming Language :: Python :: 3.10
Classifier: Programming Language :: Python :: 3.8
Classifier: Programming Language :: Python :: 3.9
Classifier: Programming Language :: Python :: Implementation :: CPython
Classifier: Topic :: Software Development :: Testing
Requires-Dist: pytest (>=7.1.1,<8.0.0)
Project-URL: Bug Tracker, https://github.com/MarximusMaximus/pytest-prefer-nested-dup-tests/issues
Project-URL: Documentation, https://github.com/MarximusMaximus/pytest-prefer-nested-dup-tests
Project-URL: Repository, https://github.com/MarximusMaximus/pytest-prefer-nested-dup-tests
Project-URL: Source, https://github.com/MarximusMaximus/pytest-prefer-nested-dup-tests
